graphviz_anywidget/__init__.py
graphviz_anywidget/static/widget.js
graphviz_anywidget-0.8.0.dist-info/METADATA
graphviz_anywidget-0.8.0.dist-info/WHEEL
graphviz_anywidget-0.8.0.dist-info/licenses/LICENSE
graphviz_anywidget-0.8.0.dist-info/RECORD
