Metadata-Version: 2.4
Name: graphviz-anywidget
Version: 0.8.0
Summary: Interactive Graphviz visualization widget for Jupyter notebooks using anywidget.
Project-URL: homepage, https://github.com/pipefunc/graphviz-anywidget
Project-URL: documentation, https://github.com/pipefunc/graphviz-anywidget
Project-URL: repository, https://github.com/pipefunc/graphviz-anywidget
Maintainer-email: Bas Nijholt <bas@nijho.lt>
License: MIT
License-File: LICENSE
Keywords: graph,graphviz,interactive,jupyter,network,visualization,widget
Classifier: Framework :: IPython
Classifier: Framework :: Jupyter
Classifier: Framework :: Jupyter :: JupyterLab
Classifier: Intended Audience :: Developers
Classifier: Intended Audience :: Science/Research
Classifier: License :: OSI Approved :: MIT License
Classifier: Operating System :: OS Independent
Classifier: Programming Language :: Python
Classifier: Programming Language :: Python :: 3
Classifier: Programming Language :: Python :: 3.10
Classifier: Programming Language :: Python :: 3.11
Classifier: Programming Language :: Python :: 3.12
Classifier: Programming Language :: Python :: 3.13
Classifier: Topic :: Scientific/Engineering :: Visualization
Classifier: Topic :: Software Development :: Libraries :: Python Modules
Classifier: Topic :: Software Development :: Widget Sets
Classifier: Typing :: Typed
Requires-Python: >=3.10
Requires-Dist: anywidget
Provides-Extra: dev
Requires-Dist: jupyterlab; extra == 'dev'
Requires-Dist: pytest; extra == 'dev'
Requires-Dist: watchfiles; extra == 'dev'
